CHANGELOG.txt
LICENSE.txt
MANIFEST.in
README.txt
setup.cfg
setup.py
distro/lucid/debian/control.template
doc/index.txt
doc/source/api.rst
doc/source/index.rst
doc/source/manual.rst
example/README.txt
test/README.txt
test/doc.py
yawn/__init__.py
yawn.egg-info/PKG-INFO
yawn.egg-info/SOURCES.txt
yawn.egg-info/dependency_links.txt
yawn.egg-info/entry_points.txt
yawn.egg-info/not-zip-safe
yawn.egg-info/requires.txt
yawn.egg-info/top_level.txt