Metadata-Version: 1.1
Name: yawn
Version: 0.1.1
Summary: Yawn is Awesome WickedNess for tests (it is a helper for selenium testing)
Home-page: https://bitbucket.org/thejimmyg/testbed
Author: James Gardner
Author-email: UNKNOWN
License: GNU AGPLv3
Platform: UNKNOWN
Classifier: Development Status :: 3 - Alpha
Classifier: License :: OSI Approved :: GNU Affero General Public License v3
Classifier: Programming Language :: Python
